itkwasm_cuberille_wasi/__init__.py
itkwasm_cuberille_wasi/_version.py
itkwasm_cuberille_wasi/cuberille.py
itkwasm_cuberille_wasi/wasm_modules/anti-alias-cuberille.wasi.wasm
itkwasm_cuberille_wasi/wasm_modules/cuberille.wasi.wasm
itkwasm_cuberille_wasi-0.2.0.dist-info/METADATA
itkwasm_cuberille_wasi-0.2.0.dist-info/WHEEL
itkwasm_cuberille_wasi-0.2.0.dist-info/RECORD
